elasticsearch_faker/__init__.py
elasticsearch_faker/__main__.py
elasticsearch_faker/__version__.py
elasticsearch_faker/_const.py
elasticsearch_faker/_es_client.py
elasticsearch_faker/_generator.py
elasticsearch_faker/_logger.py
elasticsearch_faker/_print.py
elasticsearch_faker/_provider.py
elasticsearch_faker/_template.py
elasticsearch_faker/subcmd/__init__.py
elasticsearch_faker/subcmd/provider.py
elasticsearch_faker-0.3.0.dist-info/LICENSE
elasticsearch_faker-0.3.0.dist-info/METADATA
elasticsearch_faker-0.3.0.dist-info/WHEEL
elasticsearch_faker-0.3.0.dist-info/entry_points.txt
elasticsearch_faker-0.3.0.dist-info/top_level.txt
elasticsearch_faker-0.3.0.dist-info/RECORD
