Metadata-Version: 2.1
Name: elasticsearch-faker
Version: 0.3.0
Summary: elasticsearch-faker is a CLI tool to generate fake data for Elasticsearch.
Home-page: https://github.com/thombashi/elasticsearch-faker
Author: Tsuyoshi Hombashi
Author-email: tsuyoshi.hombashi@gmail.com
License: MIT License
Project-URL: Source, https://github.com/thombashi/elasticsearch-faker
Project-URL: Tracker, https://github.com/thombashi/elasticsearch-faker/issues
Keywords: elasticsearch,faker
Classifier: Development Status :: 4 - Beta
Classifier: Environment :: Console
Classifier: Intended Audience :: Information Technology
Classifier: License :: OSI Approved :: MIT License
Classifier: Operating System :: OS Independent
Classifier: Programming Language :: Python :: 3
Classifier: Programming Language :: Python :: 3.7
Classifier: Programming Language :: Python :: 3.8
Classifier: Programming Language :: Python :: 3.9
Classifier: Programming Language :: Python :: 3.10
Classifier: Programming Language :: Python :: 3.11
Classifier: Programming Language :: Python :: 3 :: Only
Classifier: Topic :: Terminals
Requires-Python: >=3.7
License-File: LICENSE
Requires-Dist: click (<9,>=6.2)
Requires-Dist: elasticsearch (<9,>=8.0.1)
Requires-Dist: envinfopy (<1,>=0.0.3)
Requires-Dist: Faker (<19,>=1.0.8)
Requires-Dist: Jinja2 (<4,>=2.8)
Requires-Dist: loguru (<1,>=0.4.1)
Requires-Dist: Pygments (<3,>=2.2.0)
Requires-Dist: tqdm (<5,>=4.19.5)
Provides-Extra: buildexe
Requires-Dist: pyinstaller (>=5.10.1) ; extra == 'buildexe'
Requires-Dist: text-unidecode ; extra == 'buildexe'
Provides-Extra: es8
Requires-Dist: elasticsearch (<9,>=8) ; extra == 'es8'
Provides-Extra: test
Requires-Dist: Faker (==13.16) ; extra == 'test'
Requires-Dist: mock ; extra == 'test'
Requires-Dist: pytest (>=6.0.1) ; extra == 'test'
Requires-Dist: pytest-md-report (>=0.1) ; extra == 'test'
Requires-Dist: pytest-mock ; extra == 'test'
